pyllicagram/__init__.py
pyllicagram-1.8.4.dist-info/METADATA
pyllicagram-1.8.4.dist-info/WHEEL
pyllicagram-1.8.4.dist-info/top_level.txt
pyllicagram-1.8.4.dist-info/RECORD
