Metadata-Version: 2.1
Name: pyllicagram
Version: 1.8.4
Home-page: https://github.com/regicid/pyllicagram
Author: Benoit de Courson
Author-email: b.decourson@csl.mpg.de
License: Creative Commons
Keywords: example project
Requires-Dist: pandas
Requires-Dist: tqdm
